rfcorr/__init__.py
rfcorr/cat.py
rfcorr/extra_trees.py
rfcorr/random_forest.py
rfcorr/sign.py
rfcorr/xgboost.py
rfcorr-0.1.2.dist-info/LICENSE
rfcorr-0.1.2.dist-info/WHEEL
rfcorr-0.1.2.dist-info/METADATA
rfcorr-0.1.2.dist-info/RECORD
