Metadata-Version: 2.1
Name: rfcorr
Version: 0.1.2
Summary: Random Forest-inspired correlation/dependence methods
Home-page: https://github.com/mjbommar/rfcorr
License: Apache-2.0
Keywords: ml,correlation,random forest,sklearn,machine learning,dependence
Author: Michael Bommarito
Author-email: michael@bommaritollc.com
Requires-Python: >=3.8,<4.0
Classifier: License :: OSI Approved :: Apache Software License
Classifier: Programming Language :: Python :: 3
Classifier: Programming Language :: Python :: 3.8
Classifier: Programming Language :: Python :: 3.9
Classifier: Programming Language :: Python :: 3.10
Classifier: Topic :: Scientific/Engineering
Classifier: Topic :: Scientific/Engineering :: Artificial Intelligence
Classifier: Topic :: Scientific/Engineering :: Information Analysis
Classifier: Topic :: Scientific/Engineering :: Mathematics
Requires-Dist: catboost (>=1.0.4,<2.0.0)
Requires-Dist: numpy (>=1.22.2,<2.0.0)
Requires-Dist: scikit-learn (>=1.0.2,<2.0.0)
Requires-Dist: xgboost (>=1.6.0,<2.0.0)
Project-URL: Repository, https://github.com/mjbommar/rfcorr
